digital_fir_flt.v
// Design Program for Digital Finite Impulse Response (Dual) Low pass and High Pass Filters

module digital_fir_flt(
    input clk,
    input reset,
    input mode,        // 0 = low-pass, 1 = high-pass
    input signed [15:0] x_in,
    output reg signed [31:0] y_out
);

    // Delay samples
    reg signed [15:0] x_reg [0:7];

    // LP coefficients
    wire signed [15:0] lp [0:7];
    assign lp[0] = 16'sd1475;  assign lp[1] = 16'sd2950;
    assign lp[2] = 16'sd4915;  assign lp[3] = 16'sd7032;
    assign lp[4] = 16'sd7032;  assign lp[5] = 16'sd4915;
    assign lp[6] = 16'sd2950;  assign lp[7] = 16'sd1475;

    // HP coefficients
    wire signed [15:0] hp [0:7];
    assign hp[0] = -16'sd1475; assign hp[1] = -16'sd2950;
    assign hp[2] = -16'sd4915; assign hp[3] =  16'sd25742;
    assign hp[4] =  16'sd25742; assign hp[5] = -16'sd4915;
    assign hp[6] = -16'sd2950; assign hp[7] = -16'sd1475;

    // Multipliers
    wire signed [31:0] mult [0:7];
    genvar i;
    generate
        for (i = 0; i < 8; i = i + 1) begin : mul_block
            assign mult[i] = x_reg[i] * (mode ? hp[i] : lp[i]);
        end
    endgenerate

    reg signed [31:0] acc;
    integer k;

    always @(posedge clk or posedge reset) begin
        if (reset) begin
            for (k = 0; k < 8; k = k + 1)
                x_reg[k] <= 0;
            y_out <= 0;
            acc <= 0;
        end 
        else begin
            // shift register
            for (k = 7; k > 0; k = k-1)
                x_reg[k] <= x_reg[k-1];
            x_reg[0] <= x_in;

            // sum products
            acc <= mult[0] + mult[1] + mult[2] + mult[3] + mult[4] + mult[5] + mult[6] + mult[7];

            // scale back to Q15
            y_out <= acc >>> 15;
        end
    end

endmodule

digital_fir_flt_tb.v
// Testbench Program for Digital Finite Impulse Response (Dual) Low pass and High Pass Filters

`timescale 1ns/1ps

module digital_fir_flt_tb;

    reg clk, reset, mode;             // mode=0 LP, mode=1 HP
    reg  signed [15:0] x_in;
    wire signed [31:0] y_out;

    // Instantiate
    digital_fir_flt dut (.clk(clk), .reset(reset), .mode(mode), .x_in(x_in), .y_out(y_out));

    always #5 clk = ~clk; // clock

    initial begin
        $dumpfile("digital_fir_flt_tb.vcd");
        $dumpvars(0, digital_fir_flt_tb);

        clk = 0;
        reset = 1;
        mode = 0;
        x_in = 0;

        #20 reset = 0;

        // LOW PASS TEST
        mode = 0;
        $display("");
        $display("LOW PASS RESPONSE:");

        x_in = 2000; #10;
        x_in = 2000; #10;
        x_in = 2000; #10;
        x_in = 2000; #10;
        x_in = 0;    #10;
        x_in = 0;    #50;

        // HIGH PASS TEST
        mode = 1;
        $display("");
        $display("HIGH PASS RESPONSE: ");

        x_in = 2000; #10;
        x_in = 2000; #10;
        x_in = 2000; #10;
        x_in = 2000; #10;
        x_in = 0;    #10;
        x_in = 0;    #50;

        $stop;
    end

    always @(posedge clk)
        $display("t=%0t mode=%0d x_in=%d y_out=%d", $time, mode, x_in, y_out);

endmodule

digital_fir_flt_tb.vcd
$date
	Tue Dec 09 19:26:00 2025
$end
$version
	Icarus Verilog
$end
$timescale
	1ps
$end
$scope module digital_fir_flt_tb $end
$var wire 32 ! y_out [31:0] $end
$var reg 1 " clk $end
$var reg 1 # mode $end
$var reg 1 $ reset $end
$var reg 16 % x_in [15:0] $end
$scope module dut $end
$var wire 1 " clk $end
$var wire 1 # mode $end
$var wire 1 $ reset $end
$var wire 16 & x_in [15:0] $end
$var reg 32 ' acc [31:0] $end
$var reg 32 ( y_out [31:0] $end
$var integer 32 ) k [31:0] $end
$scope begin mul_block[0] $end
$var parameter 2 * i $end
$upscope $end
$scope begin mul_block[1] $end
$var parameter 2 + i $end
$upscope $end
$scope begin mul_block[2] $end
$var parameter 3 , i $end
$upscope $end
$scope begin mul_block[3] $end
$var parameter 3 - i $end
$upscope $end
$scope begin mul_block[4] $end
$var parameter 4 . i $end
$upscope $end
$scope begin mul_block[5] $end
$var parameter 4 / i $end
$upscope $end
$scope begin mul_block[6] $end
$var parameter 4 0 i $end
$upscope $end
$scope begin mul_block[7] $end
$var parameter 4 1 i $end
$upscope $end
$upscope $end
$upscope $end
$enddefinitions $end
$comment Show the parameter values. $end
$dumpall
b111 1
b110 0
b101 /
b100 .
b11 -
b10 ,
b1 +
b0 *
$end
#0
$dumpvars
b1000 )
b0 (
b0 '
b0 &
b0 %
1$
0#
0"
b0 !
$end
#5000
b1000 )
1"
#10000
0"
#15000
b1000 )
1"
#20000
0"
b11111010000 %
b11111010000 &
0$
#25000
b0 )
1"
#30000
0"
#35000
b1011010000001101110000 '
b0 )
1"
#40000
0"
#45000
b1011010 !
b1011010 (
b100001110000101001010000 '
b0 )
1"
#50000
0"
#55000
b100001110 !
b100001110 (
b1000111010000100011000000 '
b0 )
1"
#60000
0"
b0 %
b0 &
#65000
b1000111010 !
b1000111010 (
b1111100111010001001000000 '
b0 )
1"
#70000
0"
#75000
b1111100111 !
b1111100111 (
b10100111010011100001010000 '
b0 )
1"
#80000
0"
#85000
b10100111010 !
b10100111010 (
b10110110010010111111100000 '
b0 )
1"
#90000
0"
#95000
b10110110010 !
b10110110010 (
b10100111010011100001010000 '
b0 )
1"
#100000
0"
#105000
b10100111010 !
b10100111010 (
b1111100111010001001000000 '
b0 )
1"
#110000
0"
#115000
b1111100111 !
b1111100111 (
b1000111010000100011000000 '
b0 )
1"
#120000
0"
b11111010000 %
b11111010000 &
1#
#125000
b1000111010 !
b1000111010 (
b11111111011110001111010110110000 '
b0 )
1"
#130000
0"
#135000
b11111111111111111111111011110001 !
b11111111111111111111111011110001 (
b11111111101001011111100100100000 '
b0 )
1"
#140000
0"
#145000
b11111111111111111111111101001011 !
b11111111111111111111111101001011 (
b11111111011110001111010110110000 '
b0 )
1"
#150000
0"
#155000
b11111111111111111111111011110001 !
b11111111111111111111111011110001 (
b11111110111000101111011101000000 '
b0 )
1"
#160000
0"
b0 %
b0 &
#165000
b11111111111111111111110111000101 !
b11111111111111111111110111000101 (
b1111101001000110010100000 '
b0 )
1"
#170000
0"
#175000
b1111101001 !
b1111101001 (
b101001100110010010101110000 '
b0 )
1"
#180000
0"
#185000
b101001100110 !
b101001100110 (
b100111101110010110111100000 '
b0 )
1"
#190000
0"
#195000
b100111101110 !
b100111101110 (
b101001100110010010101110000 '
b0 )
1"
#200000
0"
#205000
b101001100110 !
b101001100110 (
b1111101001000110010100000 '
b0 )
1"
#210000
0"
#215000
b1111101001 !
b1111101001 (
b11111110111000101111011101000000 '
b0 )
1"
